robusta_hmf/__init__.py
robusta_hmf/_version.py
robusta_hmf/als.py
robusta_hmf/convergence.py
robusta_hmf/frame.py
robusta_hmf/hmf.py
robusta_hmf/initialisation.py
robusta_hmf/likelihoods.py
robusta_hmf/main.py
robusta_hmf/py.typed
robusta_hmf/regularisers.py
robusta_hmf/rhmf_hogg.py
robusta_hmf/rotations.py
robusta_hmf/state.py
robusta_hmf-0.0.1.dist-info/METADATA
robusta_hmf-0.0.1.dist-info/WHEEL
robusta_hmf-0.0.1.dist-info/licenses/LICENSE
robusta_hmf-0.0.1.dist-info/RECORD
