Metadata-Version: 2.4
Name: robusta-hmf
Version: 0.0.1
Summary: Robust heteroskedastic matrix factorisation in JAX.
Author-email: Tom Hilder <tom.hilder.dlhp@gmail.com>, "David W. Hogg" <TODO@TODO.com>
License-File: LICENSE
Requires-Python: >=3.13
Requires-Dist: equinox>=0.13.0
Requires-Dist: jax>=0.7.1
Requires-Dist: optax>=0.2.5
